{
  "table": "project_registry",
  "exportedAt": "2026-06-21T08:04:46.172028+00:00Z",
  "columns": [
    "eld                 T",
    "roject_id'          ",
    "roject_code'        ",
    "roject_name'        ",
    "oute_prefix'        ",
    "omain_host'         ",
    "eployment_target'   ",
    "ava_version'        ",
    "b_driver_version'   ",
    "latform_version'    ",
    "roject_module_version",
    "tatus'              ",
    "wner_admin_id'      ",
    "reated_at'          ",
    "pdated_at'          ",
    "rows selected. (0.00"
  ],
  "count": 0,
  "rows": []
}